{
  "updatedAt": "2026-07-02 07:32:13",
  "totalRows": 1585,
  "olsSampleSize": 1382,
  "byStrategy": {
    "conservative_short": {
      "total": 187,
      "wins": 52,
      "losses": 135,
      "winRate": 0.2781,
      "avgWinPct": 3.179,
      "avgLossPct": 3.317,
      "payoffRatio": 0.958,
      "avgProbability": 71.6,
      "probAccuracy": -0.438
    },
    "conservative_swing": {
      "total": 167,
      "wins": 49,
      "losses": 118,
      "winRate": 0.2934,
      "avgWinPct": 6.344,
      "avgLossPct": 5.16,
      "payoffRatio": 1.229,
      "avgProbability": 74.4,
      "probAccuracy": -0.45
    },
    "conservative_mid": {
      "total": 168,
      "wins": 57,
      "losses": 111,
      "winRate": 0.3393,
      "avgWinPct": 11.04,
      "avgLossPct": 6.966,
      "payoffRatio": 1.585,
      "avgProbability": 73.5,
      "probAccuracy": -0.396
    },
    "balanced_short": {
      "total": 158,
      "wins": 49,
      "losses": 109,
      "winRate": 0.3101,
      "avgWinPct": 4.298,
      "avgLossPct": 3.556,
      "payoffRatio": 1.208,
      "avgProbability": 72.1,
      "probAccuracy": -0.411
    },
    "balanced_swing": {
      "total": 238,
      "wins": 59,
      "losses": 179,
      "winRate": 0.2479,
      "avgWinPct": 8.482,
      "avgLossPct": 6.463,
      "payoffRatio": 1.312,
      "avgProbability": 71.6,
      "probAccuracy": -0.468
    },
    "balanced_mid": {
      "total": 166,
      "wins": 56,
      "losses": 110,
      "winRate": 0.3373,
      "avgWinPct": 12.964,
      "avgLossPct": 7.879,
      "payoffRatio": 1.645,
      "avgProbability": 74.7,
      "probAccuracy": -0.41
    },
    "aggressive_short": {
      "total": 159,
      "wins": 51,
      "losses": 108,
      "winRate": 0.3208,
      "avgWinPct": 3.943,
      "avgLossPct": 3.48,
      "payoffRatio": 1.133,
      "avgProbability": 74.3,
      "probAccuracy": -0.422
    },
    "aggressive_swing": {
      "total": 169,
      "wins": 54,
      "losses": 115,
      "winRate": 0.3195,
      "avgWinPct": 8.821,
      "avgLossPct": 6.23,
      "payoffRatio": 1.416,
      "avgProbability": 74.3,
      "probAccuracy": -0.423
    },
    "aggressive_mid": {
      "total": 173,
      "wins": 56,
      "losses": 117,
      "winRate": 0.3237,
      "avgWinPct": 13.76,
      "avgLossPct": 8.795,
      "payoffRatio": 1.564,
      "avgProbability": 74.9,
      "probAccuracy": -0.425
    }
  },
  "byMarket": {
    "kr": {
      "total": 796,
      "winRate": 0.2814,
      "avgWinPct": 7.659,
      "avgLossPct": 5.472,
      "payoffRatio": 1.4
    },
    "us": {
      "total": 789,
      "winRate": 0.3283,
      "avgWinPct": 8.783,
      "avgLossPct": 6.099,
      "payoffRatio": 1.44
    }
  },
  "byProbBand": {
    "low_50-60": {
      "count": 63,
      "actualWinRate": 0.0794
    },
    "mid_60-75": {
      "count": 576,
      "actualWinRate": 0.2986
    },
    "high_75+": {
      "count": 946,
      "actualWinRate": 0.3235
    }
  },
  "regressionFactors": {
    "intercept": {
      "coefficient": -14.4616,
      "r2": 0.0436
    },
    "rsi": {
      "coefficient": 0.2016,
      "r2": 0.0436,
      "description": "RSI14 — 높을수록 과매수 (보통 음의 계수)"
    },
    "volumeRatio": {
      "coefficient": -0.2982,
      "r2": 0.0436,
      "description": "거래량비율 — 높을수록 모멘텀 강함 (보통 양의 계수)"
    },
    "distToMa20": {
      "coefficient": -0.0722,
      "r2": 0.0436,
      "description": "MA20 이격도% — 너무 높으면 리스크 증가"
    },
    "probability": {
      "coefficient": 2.1119,
      "r2": 0.0436,
      "description": "확률 (0~1) — 모델 신뢰도"
    },
    "momentum5": {
      "coefficient": -0.0694,
      "r2": 0.0436,
      "description": "5일 모멘텀% — 단기 추세"
    },
    "_winRateRegression": {
      "r2": 0.0397,
      "sampleSize": 1382,
      "factors": {
        "rsi": 0.0115,
        "volumeRatio": -0.0079,
        "distToMa20": -0.0168,
        "probability": 0.1346,
        "momentum5": 0.0087
      }
    }
  },
  "insight": [
    "호라이즌: mid 전략 평균 승률 33.3%로 최고",
    "모드: balanced 전략 평균 payoff 1.39x로 최고",
    "마켓: US 승률 32.8%로 우위",
    "회귀분석: intercept 낮을수록 수익률 향상 (β=-14.462)",
    "전체 팩터 설명력 R²=0.043 (0~1, 높을수록 예측력 강함)",
    "Kelly 최대: conservative_short → 포트폴리오 0.0% 권장"
  ]
}